README
setup.py
bcrypt/__init__.py
bcrypt/bcrypt.c
bcrypt/bcrypt_python.c
bcrypt/blowfish.c
py3k_bcrypt.egg-info/PKG-INFO
py3k_bcrypt.egg-info/SOURCES.txt
py3k_bcrypt.egg-info/dependency_links.txt
py3k_bcrypt.egg-info/top_level.txt
test/test.py