Metadata-Version: 1.0
Name: py3k-bcrypt
Version: 0.3
Summary: Blowfish password hashing
Home-page: http://www.mindrot.org/py-bcrypt.html
Author: UNKNOWN
Author-email: UNKNOWN
License: BSD
Platform: UNKNOWN
